prova_utils.py
test_keras.py
oli_ai/__init__.py
oli_ai/cli.py
oli_ai/oli_ai.py
oli_ai/derivative/xor.py
oli_ai/maze/__init__.py
oli_ai/maze/maze.py
oli_ai/mnist_lib/__init__.py
oli_ai/mnist_lib/mnist_lib.py
oli_ai/prob/__init__.py
oli_ai/prob/prob.py
oli_ai/utils/__init__.py
oli_ai/utils/utils.py
oli_ai/vectors_lib/__init__.py
oli_ai/vectors_lib/vectors_lib.py
oli_ai-0.11.1.dist-info/AUTHORS.rst
oli_ai-0.11.1.dist-info/LICENSE
oli_ai-0.11.1.dist-info/METADATA
oli_ai-0.11.1.dist-info/WHEEL
oli_ai-0.11.1.dist-info/top_level.txt
oli_ai-0.11.1.dist-info/RECORD
