Metadata-Version: 2.1
Name: oli_ai
Version: 0.11.1
Summary: Support library for Oli AI course
Author-email: Francesco Pasqualini <frapas@gmail.com>
Maintainer-email: Francesco Pasqualini <frapas@gmail.com>
License: MIT license
Project-URL: bugs, https://github.com/frhack/oli_ai/issues
Project-URL: changelog, https://github.com/frhack/oli_ai/blob/master/changelog.md
Project-URL: homepage, https://github.com/frhack/oli_ai
License-File: LICENSE
License-File: AUTHORS.rst
Requires-Dist: typer
Provides-Extra: dev
Requires-Dist: coverage ; extra == 'dev'
Requires-Dist: mypy ; extra == 'dev'
Requires-Dist: pytest ; extra == 'dev'
Requires-Dist: ruff ; extra == 'dev'
